photos/__init__.py
photos/__main__.py
photos/check.py
photos/metadata.py
photos/organize.py
photos-0.0.5.dist-info/METADATA
photos-0.0.5.dist-info/WHEEL
photos-0.0.5.dist-info/entry_points.txt
photos-0.0.5.dist-info/top_level.txt
photos-0.0.5.dist-info/RECORD
