Metadata-Version: 2.1
Name: photos
Version: 0.0.5
Summary: Photo management utilities
Home-page: https://github.com/chbrown/photos-python
Author: Christopher Brown
Author-email: io@henrian.com
License: MIT
Platform: UNKNOWN
Requires-Python: >=3.6
